LeetCodeTools/__init__.py
LeetCodeTools/math_ops.py
LeetCodeTools/sort_ops.py
LeetCodeTools-0.4.dist-info/LICENSE
LeetCodeTools-0.4.dist-info/METADATA
LeetCodeTools-0.4.dist-info/WHEEL
LeetCodeTools-0.4.dist-info/top_level.txt
LeetCodeTools-0.4.dist-info/RECORD
